Metadata-Version: 2.1
Name: honto
Version: 0.1.0
Summary: A novel method for assessing and measuring homophily in networks
Home-page: http://github.com/fabio-cumbo/honto
Author: Fabio Cumbo
Author-email: fabio.cumbo@gmail.com
License: LICENSE
Platform: UNKNOWN
Classifier: Programming Language :: Python :: 3
Classifier: License :: OSI Approved :: MIT License
Classifier: Operating System :: OS Independent
